aurora/__init__.py
aurora/_aurora.cpython-312-i386-linux-gnu.so
aurora/adas_files.py
aurora/amdata.py
aurora/animate.py
aurora/atomic.py
aurora/coords.py
aurora/core.py
aurora/default_nml.py
aurora/example.input.gacode
aurora/facit.py
aurora/grids.f90
aurora/grids_utils.py
aurora/impden.f90
aurora/interp.py
aurora/janev_smith_rates.py
aurora/kn1d.py
aurora/main.f90
aurora/math.f90
aurora/nbi_neutrals.py
aurora/neutrals.py
aurora/oedge.py
aurora/plot_tools.py
aurora/pwi.py
aurora/radiation.py
aurora/solps.py
aurora/source_utils.py
aurora/surface.py
aurora/synth_diags.py
aurora/trim_files.py
aurora/trim_data/bulk_sputter/Ar_Be.y
aurora/trim_data/bulk_sputter/Ar_Be.ye
aurora/trim_data/bulk_sputter/Ar_Be_fit.y
aurora/trim_data/bulk_sputter/Ar_C.y
aurora/trim_data/bulk_sputter/Ar_C.ye
aurora/trim_data/bulk_sputter/Ar_C_fit.y
aurora/trim_data/bulk_sputter/Ar_W.y
aurora/trim_data/bulk_sputter/Ar_W.ye
aurora/trim_data/bulk_sputter/Ar_W_fit.y
aurora/trim_data/bulk_sputter/Be_Be.y
aurora/trim_data/bulk_sputter/Be_Be.ye
aurora/trim_data/bulk_sputter/Be_Be_fit.y
aurora/trim_data/bulk_sputter/C_C.y
aurora/trim_data/bulk_sputter/C_C.ye
aurora/trim_data/bulk_sputter/C_C_fit.y
aurora/trim_data/bulk_sputter/D_Be.y
aurora/trim_data/bulk_sputter/D_Be.ye
aurora/trim_data/bulk_sputter/D_Be_fit.y
aurora/trim_data/bulk_sputter/D_C.y
aurora/trim_data/bulk_sputter/D_C.ye
aurora/trim_data/bulk_sputter/D_C_fit.y
aurora/trim_data/bulk_sputter/D_W.y
aurora/trim_data/bulk_sputter/D_W.ye
aurora/trim_data/bulk_sputter/D_W_fit.y
aurora/trim_data/bulk_sputter/H_Be.y
aurora/trim_data/bulk_sputter/H_Be.ye
aurora/trim_data/bulk_sputter/H_Be_fit.y
aurora/trim_data/bulk_sputter/H_C.y
aurora/trim_data/bulk_sputter/H_C.ye
aurora/trim_data/bulk_sputter/H_C_fit.y
aurora/trim_data/bulk_sputter/H_W.y
aurora/trim_data/bulk_sputter/H_W.ye
aurora/trim_data/bulk_sputter/H_W_fit.y
aurora/trim_data/bulk_sputter/He_Be.y
aurorafusion-3.0.5.dist-info/METADATA
aurorafusion-3.0.5.dist-info/WHEEL
aurorafusion-3.0.5.dist-info/RECORD
aurorafusion-3.0.5.dist-info/licenses/LICENSE
