Metadata-Version: 2.2
Name: aurorafusion
Version: 3.0.5
Summary: Aurora package for particle transport, radiation and neutrals in magnetically-confined plasmas
Keywords: particle and impurity transport, neutrals, radiation, magnetic confinement fusion
Author-Email: "F. Sciortino" <sciortino@psfc.mit.edu>
Classifier: Programming Language :: Python :: 3
Project-URL: Homepage, https://github.com/fsciortino/Aurora
Requires-Dist: matplotlib
Requires-Dist: numpy<2.0.0
Requires-Dist: omfit_classes
Requires-Dist: pandas
Requires-Dist: pexpect
Requires-Dist: requests
Requires-Dist: scipy
Requires-Dist: fortranformat
Requires-Dist: netCDF4
Requires-Dist: uncertainties
Requires-Dist: omas
Requires-Dist: xarray==v2022.09.0
Requires-Dist: tqdm
Requires-Dist: matplotlib
